fluent_container/__init__.py
fluent_container/append.py
fluent_container/closure.py
fluent_container/container.py
fluent_container/traits.py
thinking_runtime/__init__.py
thinking_runtime/bootstrap.py
thinking_runtime/model.py
thinking_runtime/setup.py
thinking_runtime/defaults/__init__.py
thinking_runtime/defaults/configure_logging.py
thinking_runtime/defaults/logging_config.py
thinking_runtime/defaults/recognise_runtime.py
thinking_runtime-0.0.3.dist-info/LICENSE
thinking_runtime-0.0.3.dist-info/METADATA
thinking_runtime-0.0.3.dist-info/WHEEL
thinking_runtime-0.0.3.dist-info/top_level.txt
thinking_runtime-0.0.3.dist-info/RECORD
